ataraxis_automation/__init__.py
ataraxis_automation/automation.py
ataraxis_automation/cli.py
ataraxis_automation/py.typed
ataraxis_automation-7.0.0.dist-info/METADATA
ataraxis_automation-7.0.0.dist-info/WHEEL
ataraxis_automation-7.0.0.dist-info/entry_points.txt
ataraxis_automation-7.0.0.dist-info/licenses/LICENSE
ataraxis_automation-7.0.0.dist-info/RECORD
