Metadata-Version: 2.4
Name: ataraxis-automation
Version: 7.0.0
Summary: Supports tox-based development automation pipelines used by other Sun (NeuroAI) lab projects.
Project-URL: Homepage, https://github.com/Sun-Lab-NBB/ataraxis-automation
Project-URL: Documentation, https://ataraxis-automation-api-docs.netlify.app/
Author: Ivan Kondratyev
Maintainer-email: Ivan Kondratyev <ik278@cornell.edu>
License:                     GNU GENERAL PUBLIC LICENSE
License-File: LICENSE
Keywords: ataraxis,automation,development-tools,sunlab,tox
Classifier: Development Status :: 5 - Production/Stable
Classifier: Intended Audience :: Developers
Classifier: License :: OSI Approved :: GNU General Public License v3 or later (GPLv3+)
Classifier: Operating System :: MacOS :: MacOS X
Classifier: Operating System :: Microsoft :: Windows
Classifier: Operating System :: POSIX :: Linux
Classifier: Programming Language :: Python :: 3.12
Classifier: Programming Language :: Python :: 3.13
Classifier: Programming Language :: Python :: 3.14
Classifier: Topic :: Software Development
Classifier: Typing :: Typed
Requires-Python: <3.15,>=3.12
Requires-Dist: breathe<5,>=4
Requires-Dist: build<2,>=1
Requires-Dist: cibuildwheel[uv]<4,>=3
Requires-Dist: click<9,>=8
Requires-Dist: coverage<8,>=7
Requires-Dist: hatchling<2,>=1
Requires-Dist: importlib-metadata<9,>=8
Requires-Dist: junitparser<5,>=4
Requires-Dist: mypy<2,>=1
Requires-Dist: nanobind<3,>=2
Requires-Dist: pytest-cov<8,>=7
Requires-Dist: pytest-xdist<4,>=3
Requires-Dist: pytest<9,>=8
Requires-Dist: ruff<1,>=0
Requires-Dist: scikit-build-core<1,>=0
Requires-Dist: sphinx-autodoc-typehints<4,>=3
Requires-Dist: sphinx-click<7,>=6
Requires-Dist: sphinx-rtd-dark-mode<2,>=1
Requires-Dist: sphinx-rtd-theme<4,>=3
Requires-Dist: sphinx<9,>=8
Requires-Dist: tomli<3,>=2
Requires-Dist: twine<7,>=6
Provides-Extra: dev
Requires-Dist: tox-uv<2,>=1; extra == 'dev'
Requires-Dist: tox<5,>=4; extra == 'dev'
Requires-Dist: uv<1,>=0; extra == 'dev'
